rpio/__init__.py
rpio/__main__.py
rpio/clientLibraries/__init__.py
rpio/clientLibraries/rpclpy/CommunicationManager.py
rpio/clientLibraries/rpclpy/KnowledgeManager.py
rpio/clientLibraries/rpclpy/LoggingAndTracking.py
rpio/clientLibraries/rpclpy/__init__.py
rpio/clientLibraries/rpclpy/communication_manager.py
rpio/clientLibraries/rpclpy/knowledge.py
rpio/clientLibraries/rpclpy/node.py
rpio/clientLibraries/rpclpy/utils.py
rpio/commands/__init__.py
rpio/commands/build.py
rpio/commands/deploy.py
rpio/commands/exporter.py
rpio/commands/importer.py
rpio/commands/package.py
rpio/commands/platform.py
rpio/commands/run.py
rpio/commands/transformations.py
rpio/commands/version.py
rpio/logging/__init__.py
rpio/logging/logger.py
rpio/metamodels/__init__.py
rpio/metamodels/aadl2_IL.py
rpio/package/__init__.py
rpio/package/manager.py
rpio/parsers/__init__.py
rpio/parsers/parsers.py
rpio/parsers/robochart/__init__.py
rpio/parsers/robochart/robochart.tx
rpio/pyLauncher/__init__.py
rpio/pyLauncher/pyLauncher.py
rpio/transformations/__init__.py
rpio/transformations/transformations.py
rpio/transformations/templates/__init__.py
rpio/transformations/templates/aadl_logical.template
rpio/transformations/templates/aadl_messages.template
rpio/transformations/templates/messages_py.template
rpio/transformations/templates/mqtt_config.template
rpio/transformations/templates/redis_config.template
rpio/transformations/templates/robosapiensIO_ini.template
rpio/transformations/templates/swc_config.template
rpio/transformations/templates/swc_docker_compose.template
rpio/transformations/templates/swc_launch.template
rpio/transformations/templates/swc_launch_main.template
rpio/transformations/templates/swc_py.template
rpio/utils/__init__.py
rpio/utils/auxiliary.py
rpio/utils/constants.py
rpio/workflow/__init__.py
rpio/workflow/executer.py
rpio/workflow/tasks.py
robosapiensio-0.4.3.dist-info/LICENSE
robosapiensio-0.4.3.dist-info/METADATA
robosapiensio-0.4.3.dist-info/WHEEL
robosapiensio-0.4.3.dist-info/entry_points.txt
robosapiensio-0.4.3.dist-info/top_level.txt
robosapiensio-0.4.3.dist-info/RECORD
