Metadata-Version: 2.1
Name: robosapiensio
Version: 0.4.3
Summary: robosapiensIO - your gateway to trustworthy self-adaptive robotics.
Home-page: https://rpio.readthedocs.io/en/latest/index.html
Author: Sahar Nasimi Nezhad & Bert Van Acker
Author-email: bert.vanacker@uantwerpen.be
License: Apache License 2.0
Keywords: Robotics,Trustworthiness,self-adaptive,Model-based
Classifier: Intended Audience :: Developers
Classifier: Operating System :: OS Independent
Classifier: Programming Language :: Python
Classifier: Programming Language :: Python :: 3
Requires-Python: >=3.10
License-File: LICENSE
Requires-Dist: alabaster==1.0.0
Requires-Dist: altgraph==0.17.4
Requires-Dist: async-timeout==4.0.3
Requires-Dist: babel==2.16.0
Requires-Dist: certifi==2024.8.30
Requires-Dist: charset-normalizer==3.4.0
Requires-Dist: click==8.1.7
Requires-Dist: colorama==0.4.6
Requires-Dist: contourpy==1.3.0
Requires-Dist: cycler==0.12.1
Requires-Dist: docutils==0.21.2
Requires-Dist: fonttools==4.54.1
Requires-Dist: idna==3.10
Requires-Dist: imagesize==1.4.1
Requires-Dist: Jinja2==3.1.4
Requires-Dist: jsonpickle==3.3.0
Requires-Dist: kiwisolver==1.4.7
Requires-Dist: Markdown==3.7
Requires-Dist: markdown-it-py==3.0.0
Requires-Dist: MarkupSafe==3.0.2
Requires-Dist: matplotlib==3.9.2
Requires-Dist: mdit-py-plugins==0.4.2
Requires-Dist: mdurl==0.1.2
Requires-Dist: myst-parser==4.0.0
Requires-Dist: numpy==2.1.2
Requires-Dist: packaging==24.0
Requires-Dist: paho-mqtt==2.1.0
Requires-Dist: pefile==2023.2.7
Requires-Dist: pillow==11.0.0
Requires-Dist: portion==2.6.0
Requires-Dist: Pygments==2.18.0
Requires-Dist: pyinstaller==6.11.0
Requires-Dist: pyinstaller-hooks-contrib==2024.8
Requires-Dist: pyparsing==3.2.0
Requires-Dist: python-dateutil==2.9.0.post0
Requires-Dist: pywin32-ctypes==0.2.2
Requires-Dist: PyYAML==6.0.2
Requires-Dist: redis==5.2.0
Requires-Dist: requests==2.32.3
Requires-Dist: six==1.16.0
Requires-Dist: snowballstemmer==2.2.0
Requires-Dist: sortedcontainers==2.4.0
Requires-Dist: Sphinx==8.1.3
Requires-Dist: sphinx-markdown-tables==0.0.17
Requires-Dist: sphinx-rtd-theme==3.0.1
Requires-Dist: sphinxcontrib-applehelp==2.0.0
Requires-Dist: sphinxcontrib-devhelp==2.0.0
Requires-Dist: sphinxcontrib-htmlhelp==2.1.0
Requires-Dist: sphinxcontrib-jquery==4.1
Requires-Dist: sphinxcontrib-jsmath==1.0.1
Requires-Dist: sphinxcontrib-qthelp==2.0.0
Requires-Dist: sphinxcontrib-serializinghtml==2.0.0
Requires-Dist: tomli==2.0.2
Requires-Dist: urllib3==2.2.3
Requires-Dist: textX==4.1.0
Requires-Dist: path==17.0.0
